ckanext_oauth2-0.6.1-py3.7-nspkg.pth
ckanext/oauth2/__init__.py
ckanext/oauth2/constants.py
ckanext/oauth2/controller.py
ckanext/oauth2/db.py
ckanext/oauth2/oauth2.py
ckanext/oauth2/plugin.py
ckanext/oauth2/templates/header.html
ckanext/oauth2/tests/__init__.py
ckanext/oauth2/tests/test_controller.py
ckanext/oauth2/tests/test_db.py
ckanext/oauth2/tests/test_oauth2.py
ckanext/oauth2/tests/test_plugin.py
ckanext/oauth2/tests/test_selenium.py
ckanext_oauth2-0.6.1.dist-info/METADATA
ckanext_oauth2-0.6.1.dist-info/RECORD
ckanext_oauth2-0.6.1.dist-info/WHEEL
ckanext_oauth2-0.6.1.dist-info/entry_points.txt
ckanext_oauth2-0.6.1.dist-info/namespace_packages.txt
ckanext_oauth2-0.6.1.dist-info/top_level.txt
