Metadata-Version: 2.1
Name: ckanext-oauth2
Version: 0.6.1
Summary: OAuth2 support for CKAN
Home-page: https://github.com/conwetlab/ckanext-oauth2
Author: Aitor Magán
Author-email: amagan@conwet.com
License: UNKNOWN
Download-URL: https://github.com/conwetlab/ckanext-oauth2/tarball/v0.6.1
Keywords: CKAN,OAuth2
Platform: UNKNOWN
Classifier: Development Status :: 5 - Production/Stable
Classifier: Environment :: Web Environment
Classifier: Intended Audience :: Developers
Classifier: Programming Language :: Python :: 2
Classifier: Programming Language :: Python :: 2.7
Classifier: Programming Language :: Python
Classifier: Topic :: Internet :: WWW/HTTP :: Session
Classifier: Topic :: Internet :: WWW/HTTP :: WSGI :: Middleware
Classifier: Topic :: Software Development :: Libraries :: Python Modules
Classifier: Topic :: System :: Systems Administration :: Authentication/Directory
Requires-Dist: requests-oauthlib (==0.8.0)
